revert/__init__.py
revert/client.py
revert/core/__init__.py
revert/core/api_error.py
revert/core/client_wrapper.py
revert/core/datetime_utils.py
revert/core/jsonable_encoder.py
revert/core/remove_none_from_dict.py
revert/environment.py
revert/py.typed
revert/resources/__init__.py
revert/resources/chat/__init__.py
revert/resources/chat/client.py
revert/resources/chat/resources/__init__.py
revert/resources/chat/resources/channels/__init__.py
revert/resources/chat/resources/channels/client.py
revert/resources/chat/resources/channels/types/__init__.py
revert/resources/chat/resources/channels/types/get_channels_response.py
revert/resources/chat/resources/messages/__init__.py
revert/resources/chat/resources/messages/client.py
revert/resources/chat/resources/messages/types/__init__.py
revert/resources/chat/resources/messages/types/createor_update_message_request.py
revert/resources/chat/resources/messages/types/createor_update_message_response.py
revert/resources/chat/resources/users/__init__.py
revert/resources/chat/resources/users/client.py
revert/resources/chat/resources/users/types/__init__.py
revert/resources/chat/resources/users/types/get_users_response.py
revert/resources/common/__init__.py
revert/resources/common/resources/__init__.py
revert/resources/common/resources/associations/__init__.py
revert/resources/common/resources/associations/types/__init__.py
revert/resources/common/resources/associations/types/company_association.py
revert/resources/common/resources/associations/types/contact_association.py
revert/resources/common/resources/associations/types/deal_association.py
revert/resources/common/resources/associations/types/event_association.py
revert/resources/common/resources/associations/types/lead_association.py
revert/resources/common/resources/associations/types/task_association.py
revert/resources/common/resources/errors/__init__.py
revert/resources/common/resources/errors/errors/__init__.py
revert_api-0.0.1067.dist-info/METADATA
revert_api-0.0.1067.dist-info/WHEEL
revert_api-0.0.1067.dist-info/RECORD
